[1,["ecpdLyjvZBwrvm+cedCcQy","f8xbovb+hEeKgf3B8w+QrQ","a8XzOMS3pFl4DqpfJytkfY","04QrPDh+5MTZHEi2n/fOxE"],["node","_spriteFrame","_textureSetter","root","data"],[["cc.Node",["_name","_active","_components","_prefab","_contentSize","_trs","_parent","_children"],1,9,4,5,7,1,2],["cc.Sprite",["_sizeMode","node","_materials","_spriteFrame"],2,1,3,6],"cc.SpriteFrame",["cc.Prefab",["_name"],2],["f88687SnwNP85En5TQBzCiU",["node"],3,1],["cc.PrefabInfo",["fileId","root"],2,1]],[[5,0,1,2],[3,0,2],[0,0,7,2,3,4,5,2],[0,0,6,2,3,4,5,2],[0,0,1,6,2,3,4,5,3],[1,0,1,2,3,2],[1,1,2,1],[1,1,2,3,1],[4,0,1]],[[[{"name":"bg_dingdan","rect":[1,0,65,78],"offset":[0,0.5],"originalSize":[67,79],"capInsets":[0,0,0,0]}],[2],0,[0],[2],[1]],[[[1,"DingDanCell"],[2,"DingDanCell",[-4,-5],[[5,2,-2,[3],4],[8,-3]],[0,"ccneERtmhFUY1bYqMQyVtq",-1],[5,67,79],[0,0,0,0,0,0,1,0.6,0.6,1]],[3,"icon",1,[[6,-6,[0]]],[0,"84qcdPVMVGxJabtMgl1WRY",1],[5,93,74],[0,0,0,0,0,0,1,0.5,0.5,1]],[4,"img_tuan",false,1,[[7,-7,[1],2]],[0,"14Kn85KS9KZrDLFn/FM4EF",1],[5,29,30],[0,0,0,0,0,0,1,1.66667,1.66667,1.66667]]],0,[0,3,1,0,0,1,0,0,1,0,-1,2,0,-2,3,0,0,2,0,0,3,0,4,1,7],[0,0,0,0,0],[-1,-1,1,-1,1],[0,0,2,0,3]]]]